artbox/__init__.py
artbox/__main__.py
artbox/base.py
artbox/cli.py
artbox/py.typed
artbox/sounds.py
artbox/speech.py
artbox/videos.py
artbox-0.8.0.dist-info/LICENSE
artbox-0.8.0.dist-info/METADATA
artbox-0.8.0.dist-info/WHEEL
artbox-0.8.0.dist-info/entry_points.txt
artbox-0.8.0.dist-info/RECORD
