Metadata-Version: 2.1
Name: artbox
Version: 0.8.0
Summary: ArtBox is a tool set for handling multimedia files.
License: Other
Author: Ivan Ogasawara
Author-email: ivan.ogasawara@gmail.com
Requires-Python: >=3.9,<4
Classifier: License :: Other/Proprietary License
Classifier: Programming Language :: Python :: 3
Classifier: Programming Language :: Python :: 3.9
Classifier: Programming Language :: Python :: 3.10
Classifier: Programming Language :: Python :: 3.11
Classifier: Programming Language :: Python :: 3.12
Requires-Dist: aubio (>=0.4.9)
Requires-Dist: edge-tts (>=6.1.8)
Requires-Dist: ffmpeg-python (>=0.2.0)
Requires-Dist: google-cloud-speech (>=2.24.1)
Requires-Dist: gtts (>=2.3.2)
Requires-Dist: librosa (>=0.10.1)
Requires-Dist: matplotlib (<=3.9)
Requires-Dist: moviepy (>=1.0.3)
Requires-Dist: noisereduce (>=2.0.1,<3)
Requires-Dist: numpy (>=1.20,<2)
Requires-Dist: openai (>=1)
Requires-Dist: pycairo (>=1.24.0,<1.26)
Requires-Dist: pydub (>=0.25.1)
Requires-Dist: pygobject (>=3.44.1)
Requires-Dist: python-dotenv (>=1.0.0)
Requires-Dist: pytubefix (>=5.0)
Requires-Dist: scipy (<1.23)
Requires-Dist: speechrecognition (>=3.10)
Requires-Dist: typer (>=0.9.0)
Requires-Dist: vosk (>=0.3.45)
